setup.py
trunity_3_client/__init__.py
trunity_3_client.egg-info/PKG-INFO
trunity_3_client.egg-info/SOURCES.txt
trunity_3_client.egg-info/dependency_links.txt
trunity_3_client.egg-info/requires.txt
trunity_3_client.egg-info/top_level.txt
trunity_3_client/builders/__init__.py
trunity_3_client/builders/qst_pool.py
trunity_3_client/clients/__init__.py
trunity_3_client/clients/auth.py
trunity_3_client/clients/client.py
trunity_3_client/clients/endpoints/__init__.py
trunity_3_client/clients/endpoints/contents.py
trunity_3_client/clients/endpoints/questions.py
trunity_3_client/clients/endpoints/remote_files.py
trunity_3_client/clients/endpoints/sites.py
trunity_3_client/clients/endpoints/terms.py
trunity_3_client/clients/endpoints/topics.py
trunity_3_client/utils/__init__.py
trunity_3_client/utils/url.py
trunity_3_client/utils/tests/__init__.py
trunity_3_client/utils/tests/test_url.py