Metadata-Version: 1.0
Name: trunity-3-client
Version: 0.6.1
Summary: API client for Trunity 3 learning platform and more
Home-page: UNKNOWN
Author: hunting
Author-email: VicHuntig@yandex.ua
License: MIT
Platform: UNKNOWN
